eagexp/__init__.py
eagexp/about.py
eagexp/airwires.py
eagexp/cmd.py
eagexp/exp.py
eagexp/image.py
eagexp/image3d.py
eagexp/partlist.py
eagexp/util.py
eagexp/version.py
eagexp/eagle3d/3d50.ulp
eagexp/eagle3d/3dcol_e.dat
eagexp/eagle3d/3dconf.dat
eagexp/eagle3d/3dfunc41.ulp
eagexp/eagle3d/3dfunc50.ulp
eagexp/eagle3d/3dlang_e.dat
eagexp/eagle3d/3dpack.dat
eagexp/eagle3d/3dusrpac.dat
eagexp/eagle3d/COPYING
eagexp/eagle3d/DejaVuLGCSans-Bold.ttf
eagexp/eagle3d/DejaVuLGCSans.ttf
eagexp/eagle3d/DejaVuLGCSansMono-Bold.ttf
eagexp/eagle3d/DejaVuLGCSansMono.ttf
eagexp/eagle3d/README
eagexp/eagle3d/alphalcd.ttf
eagexp/eagle3d/e3d_cap.inc
eagexp/eagle3d/e3d_connector.inc
eagexp/eagle3d/e3d_diode.inc
eagexp/eagle3d/e3d_ic.inc
eagexp/eagle3d/e3d_qfp.inc
eagexp/eagle3d/e3d_resistor.inc
eagexp/eagle3d/e3d_socket.inc
eagexp/eagle3d/e3d_special.inc
eagexp/eagle3d/e3d_switch.inc
eagexp/eagle3d/e3d_tex.inc
eagexp/eagle3d/e3d_tools.inc
eagexp/eagle3d/e3d_trafo.inc
eagexp/eagle3d/e3d_transistor.inc
eagexp/eagle3d/e3d_user.inc
eagexp/eagle3d/eagle2svg.ulp
eagexp/eagle3d/eagle3d.ttf
eagexp/eagle3d/tex_elko.png
eagexp/eagle3d/tex_elko_axial.png
eagexp/examples/__init__.py
eagexp/examples/airwires.py
eagexp/examples/image3d_example.py
eagexp/examples/image_example.py
eagexp/examples/partlist_example.py
eagexp-0.3.dist-info/LICENSE.txt
eagexp-0.3.dist-info/METADATA
eagexp-0.3.dist-info/WHEEL
eagexp-0.3.dist-info/top_level.txt
eagexp-0.3.dist-info/RECORD
