Metadata-Version: 2.1
Name: eagexp
Version: 0.3
Summary: export eagle schematic or board to image or partlist
Home-page: https://github.com/ponty/eagexp
Author: ponty
License: BSD
Keywords: eagle
Platform: UNKNOWN
Classifier: License :: OSI Approved :: BSD License
Classifier: Natural Language :: English
Classifier: Programming Language :: Python
Classifier: Programming Language :: Python :: 3
Classifier: Programming Language :: Python :: 3.7
Classifier: Programming Language :: Python :: 3.8
Classifier: Programming Language :: Python :: 3.9
Requires-Dist: PyScreenshot
Requires-Dist: PyUserInput
Requires-Dist: backports.tempfile
Requires-Dist: easyprocess
Requires-Dist: pillow
Requires-Dist: pyvirtualdisplay
